opensipscli/__init__.py
opensipscli/args.py
opensipscli/cli.py
opensipscli/comm.py
opensipscli/config.py
opensipscli/db.py
opensipscli/defaults.py
opensipscli/logger.py
opensipscli/main.py
opensipscli/module.py
opensipscli/version.py
opensipscli/libs/__init__.py
opensipscli/libs/sqlalchemy_utils.py
opensipscli/modules/__init__.py
opensipscli/modules/database.py
opensipscli/modules/diagnose.py
opensipscli/modules/instance.py
opensipscli/modules/mi.py
opensipscli/modules/tls.py
opensipscli/modules/trace.py
opensipscli/modules/trap.py
opensipscli/modules/user.py
opensipscli-0.3.1.data/scripts/opensips-cli
opensipscli-0.3.1.dist-info/LICENSE
opensipscli-0.3.1.dist-info/METADATA
opensipscli-0.3.1.dist-info/WHEEL
opensipscli-0.3.1.dist-info/top_level.txt
opensipscli-0.3.1.dist-info/RECORD
