Metadata-Version: 2.1
Name: opensipscli
Version: 0.3.1
Summary: OpenSIPS Command Line Interface
Home-page: https://github.com/OpenSIPS/opensips-cli
Download-URL: https://github.com/OpenSIPS/opensips-cli/archive/master.zip
Author: OpenSIPS Project
Author-email: project@opensips.org
Maintainer: Razvan Crainea
Maintainer-email: razvan@opensips.org
Project-URL: Source Code, https://github.com/OpenSIPS/opensips-cli
Project-URL: Issues Tracker, https://github.com/OpenSIPS/opensips-cli/issues
Classifier: Programming Language :: Python :: 3
Classifier: License :: OSI Approved :: GNU General Public License v3 (GPLv3)
Classifier: Operating System :: OS Independent
License-File: LICENSE
Requires-Dist: opensips
Requires-Dist: mysqlclient<1.4.0rc1
Requires-Dist: sqlalchemy<2,>=1.3.3
Requires-Dist: sqlalchemy-utils
